recordskeeper_python_lib/__init__.py
recordskeeper_python_lib/address.py
recordskeeper_python_lib/assets.py
recordskeeper_python_lib/block.py
recordskeeper_python_lib/blockchain.py
recordskeeper_python_lib/permissions.py
recordskeeper_python_lib/stream.py
recordskeeper_python_lib/transaction.py
recordskeeper_python_lib/wallet.py
recordskeeper_python_lib/test/__init__.py
recordskeeper_python_lib/test/test_address.py
recordskeeper_python_lib/test/test_assets.py
recordskeeper_python_lib/test/test_block.py
recordskeeper_python_lib/test/test_blockchain.py
recordskeeper_python_lib/test/test_permissions.py
recordskeeper_python_lib/test/test_stream.py
recordskeeper_python_lib/test/test_transaction.py
recordskeeper_python_lib/test/test_wallet.py
recordskeeper_python_lib-0.1.9.dist-info/DESCRIPTION.rst
recordskeeper_python_lib-0.1.9.dist-info/METADATA
recordskeeper_python_lib-0.1.9.dist-info/RECORD
recordskeeper_python_lib-0.1.9.dist-info/WHEEL
recordskeeper_python_lib-0.1.9.dist-info/metadata.json
recordskeeper_python_lib-0.1.9.dist-info/top_level.txt
