Metadata-Version: 2.0
Name: recordskeeper-python-lib
Version: 0.1.9
Summary: RecordsKeeper Python library
Home-page: https://github.com/RecordsKeeper/recordskeeper-python-sdk
Author: UNKNOWN
Author-email: UNKNOWN
License: UNKNOWN
Requires-Dist: requests
Requires-Dist: green
Requires-Dist: pyyaml
